partitions/__init__.py
partitions/main.py
partitions/partitions.py
partitions-1.0.0.dist-info/LICENSE
partitions-1.0.0.dist-info/METADATA
partitions-1.0.0.dist-info/WHEEL
partitions-1.0.0.dist-info/entry_points.txt
partitions-1.0.0.dist-info/top_level.txt
partitions-1.0.0.dist-info/RECORD
