Metadata-Version: 2.1
Name: partitions
Version: 1.0.0
Summary: Generates partitions of a positive integer
Home-page: https://github.com/mbanders/partitions.git
Author: Michael Anderson
License: UNKNOWN
Platform: UNKNOWN
Classifier: Programming Language :: Python :: 3
Classifier: License :: OSI Approved :: MIT License
Requires-Python: >3.5.0
